cdblib/cdblib.py
cdblib/compat.py
cdblib/_djb_hash.cpython-39-x86_64-linux-gnu.so
cdblib/__init__.py
cdblib/cdbmake.py
cdblib/djb_hash.py
cdblib/cdbdump.py
pure_cdb-4.0.0.dist-info/RECORD
pure_cdb-4.0.0.dist-info/WHEEL
pure_cdb-4.0.0.dist-info/METADATA
pure_cdb-4.0.0.dist-info/top_level.txt
pure_cdb-4.0.0.dist-info/entry_points.txt
pure_cdb-4.0.0.dist-info/LICENSE
