Metadata-Version: 2.1
Name: pure-cdb
Version: 4.0.0
Summary: Pure Python reader/writer for Dan J. Berstein's CDB format.
Home-page: UNKNOWN
Author: David Wilson
Author-email: dw@botanicus.net
License: MIT
Download-URL: https://github.com/dw/python-pure-cdb
Keywords: cdb file format appengine database db
Platform: UNKNOWN
Requires-Python: >=3.6
License-File: LICENSE
